storyteller/__init__.py
storyteller/cli.py
storyteller/config.py
storyteller/model.py
storyteller/utils.py
storyteller_core-0.0.4.dist-info/LICENSE
storyteller_core-0.0.4.dist-info/METADATA
storyteller_core-0.0.4.dist-info/WHEEL
storyteller_core-0.0.4.dist-info/entry_points.txt
storyteller_core-0.0.4.dist-info/RECORD
