Metadata-Version: 2.1
Name: storyteller-core
Version: 0.0.4
Summary: Multimodal AI Story Teller, built with Stable Diffusion, GPT, and neural text-to-speech
License: MIT
Author: Jaesung Tae
Author-email: jaesungtae@gmail.com
Requires-Python: >=3.8,<3.11
Classifier: License :: OSI Approved :: MIT License
Classifier: Programming Language :: Python :: 3
Classifier: Programming Language :: Python :: 3.8
Classifier: Programming Language :: Python :: 3.9
Classifier: Programming Language :: Python :: 3.10
Requires-Dist: diffusers (>=0.11.1,<0.12.0)
Requires-Dist: nltk (>=3.8.1,<4.0.0)
Requires-Dist: pre-commit[dev] (>=2.21.0,<3.0.0)
Requires-Dist: soundfile (>=0.11.0,<0.12.0)
Requires-Dist: transformers (>=4.25.1,<5.0.0)
Requires-Dist: tts (>=0.10.1,<0.11.0)
